{
    "id": "enanitos-verdes-ale-lerner-amigos",
    "title": "Amigos",
    "artist": "Enanitos Verdes y Ale Lerner",
    "originalKey": "C",
    "tempo": "Moderato",
    "timeSignature": "4/4",
    "content": [
      {
        "type": "section",
        "name": "ESTROFA 1",
        "lines": [
          {
            "type": "voice",
            "name": "1º VOZ ALE",
            "color": "ale",
            "lines": [
              {
                "type": "chord",
                "content": "C"
              },
              {
                "type": "lyric",
                "content": "No importa el lugar,"
              }
            ]
          },
          {
            "type": "voice",
            "name": "1º VOZ PATO",
            "color": "pato",
            "lines": [
              {
                "type": "chord",
                "content": "G"
              },
              {
                "type": "lyric",
                "content": ""
              }
            ]
          },
          {
            "type": "voice",
            "name": "1º VOZ ALE",
            "color": "ale",
            "lines": [
              {
                "type": "chord",
                "content": "Am"
              },
              {
                "type": "lyric",
                "content": "el sol es siempre igual"
              }
            ]
          },
          {
            "type": "voice",
            "name": "1º VOZ PATO",
            "color": "pato",
            "lines": [
              {
                "type": "chord",
                "content": "Em"
              },
              {
                "type": "lyric",
                "content": ""
              }
            ]
          },
          {
            "type": "voice",
            "name": "1º VOZ ALE",
            "color": "ale",
            "lines": [
              {
                "type": "chord",
                "content": "F"
              },
              {
                "type": "lyric",
                "content": "No importa si es recuerdo"
              }
            ]
          },
          {
            "type": "voice",
            "name": "1º VOZ PATO",
            "color": "pato",
            "lines": [
              {
                "type": "chord",
                "content": "C"
              },
              {
                "type": "lyric",
                "content": ""
              }
            ]
          },
          {
            "type": "voice",
            "name": "1º VOZ ALE",
            "color": "ale",
            "lines": [
              {
                "type": "chord",
                "content": "G"
              },
              {
                "type": "lyric",
                "content": "es algo que vendrá"
              }
            ]
          },
          {
            "type": "chords",
            "content": ["G7"]
          }
        ]
      },
      {
        "type": "divider"
      },
      {
        "type": "section",
        "name": "ESTROFA 2",
        "lines": [
          {
            "type": "voice",
            "name": "1º VOZ ALE",
            "color": "ale",
            "lines": [
              {
                "type": "chord",
                "content": "C"
              },
              {
                "type": "lyric",
                "content": "No importa cuánto hay"
              }
            ]
          },
          {
            "type": "voice",
            "name": "1º VOZ PATO",
            "color": "pato",
            "lines": [
              {
                "type": "chord",
                "content": "G"
              },
              {
                "type": "lyric",
                "content": ""
              },
              {
                "type": "chord",
                "content": "G9"
              },
              {
                "type": "lyric",
                "content": ""
              }
            ]
          },
          {
            "type": "voice",
            "name": "1º VOZ ALE",
            "color": "ale",
            "lines": [
              {
                "type": "chord",
                "content": "Am"
              },
              {
                "type": "lyric",
                "content": "en tus bolsillos hoy"
              }
            ]
          },
          {
            "type": "voice",
            "name": "1º VOZ PATO",
            "color": "pato",
            "lines": [
              {
                "type": "chord",
                "content": "Em"
              },
              {
                "type": "lyric",
                "content": ""
              }
            ]
          },
          {
            "type": "voice",
            "name": "1º VOZ ALE",
            "color": "ale",
            "lines": [
              {
                "type": "chord",
                "content": "F"
              },
              {
                "type": "lyric",
                "content": "sin nada hemos venido"
              }
            ]
          },
          {
            "type": "voice",
            "name": "1º VOZ PATO",
            "color": "pato",
            "lines": [
              {
                "type": "chord",
                "content": "C"
              },
              {
                "type": "lyric",
                "content": ""
              }
            ]
          },
          {
            "type": "voice",
            "name": "1º VOZ ALE",
            "color": "ale",
            "lines": [
              {
                "type": "chord",
                "content": "G"
              },
              {
                "type": "lyric",
                "content": "y nos iremos igual"
              }
            ]
          },
          {
            "type": "chords",
            "content": ["G7"]
          }
        ]
      },
      {
        "type": "divider"
      },
      {
        "type": "section",
        "name": "PRE-ESTRIBILLO",
        "lines": [
          {
            "type": "voice",
            "name": "1º VOZ ALE",
            "color": "ale",
            "lines": [
              {
                "type": "chord",
                "content": "C"
              },
              {
                "type": "lyric",
                "content": "Porque siempre estarán en mí"
              }
            ]
          },
          {
            "type": "voice",
            "name": "1º VOZ PATO",
            "color": "pato",
            "lines": [
              {
                "type": "chord",
                "content": "G"
              },
              {
                "type": "lyric",
                "content": ""
              }
            ]
          },
          {
            "type": "voice",
            "name": "1º VOZ ALE",
            "color": "ale",
            "lines": [
              {
                "type": "chord",
                "content": "Am"
              },
              {
                "type": "lyric",
                "content": ""
              }
            ]
          },
          {
            "type": "voice",
            "name": "1º VOZ PATO",
            "color": "pato",
            "lines": [
              {
                "type": "chord",
                "content": "F"
              },
              {
                "type": "lyric",
                "content": "esos buenos momentos que"
              }
            ]
          },
          {
            "type": "voice",
            "name": "1º VOZ ALE",
            "color": "ale",
            "lines": [
              {
                "type": "chord",
                "content": "D7"
              },
              {
                "type": "lyric",
                "content": ""
              }
            ]
          },
          {
            "type": "voice",
            "name": "1º VOZ PATO",
            "color": "pato",
            "lines": [
              {
                "type": "chord",
                "content": "G"
              },
              {
                "type": "lyric",
                "content": "pasamos sin saber."
              }
            ]
          },
          {
            "type": "chords",
            "content": ["G7"]
          }
        ]
      },
      {
        "type": "divider"
      },
      {
        "type": "section",
        "name": "ESTROFA 3",
        "lines": [
          {
            "type": "voice",
            "name": "1º VOZ ALE",
            "color": "ale",
            "lines": [
              {
                "type": "chord",
                "content": "C"
              },
              {
                "type": "lyric",
                "content": "No importa dónde estás"
              }
            ]
          },
          {
            "type": "voice",
            "name": "1º VOZ PATO",
            "color": "pato",
            "lines": [
              {
                "type": "chord",
                "content": "G"
              },
              {
                "type": "lyric",
                "content": ""
              }
            ]
          },
          {
            "type": "voice",
            "name": "1º VOZ ALE",
            "color": "ale",
            "lines": [
              {
                "type": "chord",
                "content": "Am"
              },
              {
                "type": "lyric",
                "content": "si vienes o si vas"
              }
            ]
          },
          {
            "type": "voice",
            "name": "1º VOZ PATO",
            "color": "pato",
            "lines": [
              {
                "type": "chord",
                "content": "Em"
              },
              {
                "type": "lyric",
                "content": ""
              }
            ]
          },
          {
            "type": "voice",
            "name": "1º VOZ ALE",
            "color": "ale",
            "lines": [
              {
                "type": "chord",
                "content": "F"
              },
              {
                "type": "lyric",
                "content": "La vida es un camino"
              }
            ]
          },
          {
            "type": "voice",
            "name": "1º VOZ PATO",
            "color": "pato",
            "lines": [
              {
                "type": "chord",
                "content": "C"
              },
              {
                "type": "lyric",
                "content": ""
              }
            ]
          },
          {
            "type": "voice",
            "name": "1º VOZ ALE",
            "color": "ale",
            "lines": [
              {
                "type": "chord",
                "content": "G"
              },
              {
                "type": "lyric",
                "content": "un camino para andar"
              }
            ]
          },
          {
            "type": "chords",
            "content": ["G7"]
          }
        ]
      },
      {
        "type": "divider"
      },
      {
        "type": "section",
        "name": "ESTROFA 4",
        "lines": [
          {
            "type": "voice",
            "name": "1º VOZ ALE",
            "color": "ale",
            "lines": [
              {
                "type": "chord",
                "content": "C"
              },
              {
                "type": "lyric",
                "content": "Si hay algo que esconder"
              }
            ]
          },
          {
            "type": "voice",
            "name": "1º VOZ PATO",
            "color": "pato",
            "lines": [
              {
                "type": "chord",
                "content": "G"
              },
              {
                "type": "lyric",
                "content": ""
              },
              {
                "type": "chord",
                "content": "G9"
              },
              {
                "type": "lyric",
                "content": ""
              }
            ]
          },
          {
            "type": "voice",
            "name": "1º VOZ ALE",
            "color": "ale",
            "lines": [
              {
                "type": "chord",
                "content": "Am"
              },
              {
                "type": "lyric",
                "content": "o hay algo que decir"
              }
            ]
          },
          {
            "type": "voice",
            "name": "1º VOZ PATO",
            "color": "pato",
            "lines": [
              {
                "type": "chord",
                "content": "Em"
              },
              {
                "type": "lyric",
                "content": ""
              }
            ]
          },
          {
            "type": "voice",
            "name": "1º VOZ ALE",
            "color": "ale",
            "lines": [
              {
                "type": "chord",
                "content": "F"
              },
              {
                "type": "lyric",
                "content": "siempre será un amigo"
              }
            ]
          },
          {
            "type": "voice",
            "name": "1º VOZ PATO",
            "color": "pato",
            "lines": [
              {
                "type": "chord",
                "content": "C"
              },
              {
                "type": "lyric",
                "content": ""
              }
            ]
          },
          {
            "type": "voice",
            "name": "1º VOZ ALE",
            "color": "ale",
            "lines": [
              {
                "type": "chord",
                "content": "G"
              },
              {
                "type": "lyric",
                "content": "el primero en saber"
              }
            ]
          },
          {
            "type": "chords",
            "content": ["G7"]
          }
        ]
      },
      {
        "type": "divider"
      },
      {
        "type": "section",
        "name": "PRE-ESTRIBILLO (REPETICIÓN)",
        "lines": [
          {
            "type": "voice",
            "name": "1º VOZ ALE",
            "color": "ale",
            "lines": [
              {
                "type": "chord",
                "content": "C"
              },
              {
                "type": "lyric",
                "content": "Porque siempre estarán en mí"
              }
            ]
          },
          {
            "type": "voice",
            "name": "1º VOZ PATO",
            "color": "pato",
            "lines": [
              {
                "type": "chord",
                "content": "G"
              },
              {
                "type": "lyric",
                "content": ""
              }
            ]
          },
          {
            "type": "voice",
            "name": "1º VOZ ALE",
            "color": "ale",
            "lines": [
              {
                "type": "chord",
                "content": "Am"
              },
              {
                "type": "lyric",
                "content": ""
              }
            ]
          },
          {
            "type": "voice",
            "name": "1º VOZ PATO",
            "color": "pato",
            "lines": [
              {
                "type": "chord",
                "content": "F"
              },
              {
                "type": "lyric",
                "content": "esos buenos momentos que"
              }
            ]
          },
          {
            "type": "voice",
            "name": "1º VOZ ALE",
            "color": "ale",
            "lines": [
              {
                "type": "chord",
                "content": "D7"
              },
              {
                "type": "lyric",
                "content": ""
              }
            ]
          },
          {
            "type": "voice",
            "name": "1º VOZ PATO",
            "color": "pato",
            "lines": [
              {
                "type": "chord",
                "content": "G"
              },
              {
                "type": "lyric",
                "content": "pasamos sin saber."
              }
            ]
          },
          {
            "type": "chords",
            "content": ["G7"]
          }
        ]
      },
      {
        "type": "divider"
      },
      {
        "type": "section",
        "name": "SOLO DE PIANO",
        "lines": [
          {
            "type": "text",
            "content": "Solo Piano: SOL / SI / SI / SOL / MI / SOL / LA / DO+1 / DO+1 / LA+1 / SOL+1 / MI+1 / RE+1 / DO+1 / (De nuevo lento) / SI / DO+1 / RE+1 / RE+1"
          }
        ]
      },
      {
        "type": "divider"
      },
      {
        "type": "section",
        "name": "ESTRIBILLO",
        "lines": [
          {
            "type": "voice",
            "name": "1º VOZ ALE",
            "color": "ale",
            "lines": [
              {
                "type": "chord",
                "content": "C"
              },
              {
                "type": "lyric",
                "content": "Que un amigo es una luz"
              }
            ]
          },
          {
            "type": "voice",
            "name": "1º VOZ PATO",
            "color": "pato",
            "lines": [
              {
                "type": "chord",
                "content": "F"
              },
              {
                "type": "lyric",
                "content": ""
              },
              {
                "type": "chord",
                "content": "G"
              },
              {
                "type": "lyric",
                "content": ""
              }
            ]
          },
          {
            "type": "voice",
            "name": "1º VOZ ALE",
            "color": "ale",
            "lines": [
              {
                "type": "chord",
                "content": "C"
              },
              {
                "type": "lyric",
                "content": "brillando en la oscuridad"
              }
            ]
          },
          {
            "type": "voice",
            "name": "1º VOZ PATO",
            "color": "pato",
            "lines": [
              {
                "type": "chord",
                "content": "G"
              },
              {
                "type": "lyric",
                "content": ""
              },
              {
                "type": "chord",
                "content": "Am"
              },
              {
                "type": "lyric",
                "content": ""
              }
            ]
          },
          {
            "type": "voice",
            "name": "1º VOZ ALE",
            "color": "ale",
            "lines": [
              {
                "type": "chord",
                "content": "F"
              },
              {
                "type": "lyric",
                "content": "siempre serás mi amigo"
              }
            ]
          },
          {
            "type": "voice",
            "name": "1º VOZ PATO",
            "color": "pato",
            "lines": [
              {
                "type": "chord",
                "content": "G"
              },
              {
                "type": "lyric",
                "content": ""
              }
            ]
          },
          {
            "type": "voice",
            "name": "1º VOZ ALE",
            "color": "ale",
            "lines": [
              {
                "type": "chord",
                "content": "C"
              },
              {
                "type": "lyric",
                "content": "no importa nada más."
              }
            ]
          }
        ]
      },
      {
        "type": "divider"
      },
      {
        "type": "section",
        "name": "ESTRIBILLO (REPETICIÓN X2)",
        "lines": [
          {
            "type": "voice",
            "name": "1º VOZ ALE",
            "color": "ale",
            "lines": [
              {
                "type": "chord",
                "content": "C"
              },
              {
                "type": "lyric",
                "content": "Que un amigo es una luz"
              }
            ]
          },
          {
            "type": "voice",
            "name": "1º VOZ PATO",
            "color": "pato",
            "lines": [
              {
                "type": "chord",
                "content": "F"
              },
              {
                "type": "lyric",
                "content": ""
              },
              {
                "type": "chord",
                "content": "G"
              },
              {
                "type": "lyric",
                "content": ""
              }
            ]
          },
          {
            "type": "voice",
            "name": "1º VOZ ALE",
            "color": "ale",
            "lines": [
              {
                "type": "chord",
                "content": "C"
              },
              {
                "type": "lyric",
                "content": "brillando en la oscuridad"
              }
            ]
          },
          {
            "type": "voice",
            "name": "1º VOZ PATO",
            "color": "pato",
            "lines": [
              {
                "type": "chord",
                "content": "G"
              },
              {
                "type": "lyric",
                "content": ""
              },
              {
                "type": "chord",
                "content": "Am"
              },
              {
                "type": "lyric",
                "content": ""
              }
            ]
          },
          {
            "type": "voice",
            "name": "1º VOZ ALE",
            "color": "ale",
            "lines": [
              {
                "type": "chord",
                "content": "F"
              },
              {
                "type": "lyric",
                "content": "siempre serás mi amigo"
              }
            ]
          },
          {
            "type": "voice",
            "name": "1º VOZ PATO",
            "color": "pato",
            "lines": [
              {
                "type": "chord",
                "content": "G"
              },
              {
                "type": "lyric",
                "content": ""
              }
            ]
          },
          {
            "type": "voice",
            "name": "1º VOZ ALE",
            "color": "ale",
            "lines": [
              {
                "type": "chord",
                "content": "C"
              },
              {
                "type": "lyric",
                "content": "no importa nada más."
              }
            ]
          },
          {
            "type": "text",
            "content": "(Repetir 2 veces)"
          }
        ]
      }
    ]
  }
  